simple_transforms-0.2.0.dist-info/METADATA
simple_transforms-0.2.0.dist-info/WHEEL
simple_transforms-0.2.0.dist-info/copying.md
simple_transforms-0.2.0.dist-info/RECORD
simple_transforms-0.2.0.dist-info/copying.lesser.md
simple_transforms-0.2.0.dist-info/top_level.txt
simple_transforms/pytrans.c
simple_transforms/_c_trans.cpython-310-x86_64-linux-gnu.so
simple_transforms/__init__.py
