Metadata-Version: 2.1
Name: simple-transforms
Version: 0.2.0
Summary: Simple 4x4 transfomation matrices as numpy arrays
Author-email: Jef Wagner <jefwagner@gmail.com>
License: LGPL-3.0-or-later
Project-URL: Homepage, https://jefwagner.github.io/transforms
Project-URL: Bug Tracker, https://github.com/jefwagner/simple-transforms/issues
Keywords: CAD
Requires-Python: >=3.8
License-File: copying.lesser.md
License-File: copying.md
Requires-Dist: numpy >=1.17.3
Provides-Extra: flint
Requires-Dist: numpy-flint >=0.3.3 ; extra == 'flint'
